robotlibraryproxy/__init__.py
robotlibraryproxy/__version__.py
robotlibraryproxy/py.typed
robotframework_libraryproxy-0.3.0.dist-info/LICENSE
robotframework_libraryproxy-0.3.0.dist-info/METADATA
robotframework_libraryproxy-0.3.0.dist-info/WHEEL
robotframework_libraryproxy-0.3.0.dist-info/RECORD
