Metadata-Version: 2.1
Name: robotframework-libraryproxy
Version: 0.3.0
Summary: Call RobotFramework keywords from Python
Home-page: https://github.com/d-biehl/robotframework-libraryproxy
License: Apache-2.0
Keywords: Test,Testing,RobotFramework
Author: Daniel Biehl
Author-email: dbiehl@live.de
Requires-Python: >=3.10,<4.0
Classifier: Development Status :: 5 - Production/Stable
Classifier: Framework :: Robot Framework
Classifier: Framework :: Robot Framework :: Tool
Classifier: License :: OSI Approved :: Apache Software License
Classifier: Operating System :: OS Independent
Classifier: Programming Language :: Python :: 3
Classifier: Programming Language :: Python :: 3.10
Classifier: Programming Language :: Python :: 3.11
Classifier: Programming Language :: Python :: 3.12
Classifier: Programming Language :: Python :: 3.8
Classifier: Programming Language :: Python :: 3.9
Classifier: Programming Language :: Python :: Implementation
Classifier: Topic :: Software Development :: Testing
Classifier: Topic :: Software Development :: Testing :: Acceptance
Classifier: Typing :: Typed
Requires-Dist: robotframework
Project-URL: Repository, https://github.com/d-biehl/robotframework-libraryproxy
